setup.py
dsnd_distributions_turuu/Binomialdistribution.py
dsnd_distributions_turuu/Gaussiandistribution.py
dsnd_distributions_turuu/Generaldistribution.py
dsnd_distributions_turuu/__init__.py
dsnd_distributions_turuu.egg-info/PKG-INFO
dsnd_distributions_turuu.egg-info/SOURCES.txt
dsnd_distributions_turuu.egg-info/dependency_links.txt
dsnd_distributions_turuu.egg-info/not-zip-safe
dsnd_distributions_turuu.egg-info/top_level.txt