Metadata-Version: 1.0
Name: dsnd-distributions-turuu
Version: 1.1
Summary: Gaussian distributions
Home-page: UNKNOWN
Author: Turuu
Author-email: Turuuemail@email.com
License: UNKNOWN
Platform: UNKNOWN
